rekuest/__init__.py
rekuest/actors/__init__.py
rekuest/actors/actify.py
rekuest/actors/base.py
rekuest/actors/contexts.py
rekuest/actors/errors.py
rekuest/actors/functional.py
rekuest/actors/helper.py
rekuest/actors/reactive/__init__.py
rekuest/actors/reactive/api.py
rekuest/actors/transport/__init__.py
rekuest/actors/transport/local_transport.py
rekuest/actors/transport/queue_transport.py
rekuest/actors/transport/types.py
rekuest/actors/types.py
rekuest/actors/vars.py
rekuest/agents/__init__.py
rekuest/agents/base.py
rekuest/agents/errors.py
rekuest/agents/extension.py
rekuest/agents/hooks.py
rekuest/agents/transport/__init__.py
rekuest/agents/transport/base.py
rekuest/agents/transport/errors.py
rekuest/agents/transport/mock.py
rekuest/agents/transport/protocols/__init__.py
rekuest/agents/transport/protocols/agent_json.py
rekuest/agents/transport/websocket.py
rekuest/api/__init__.py
rekuest/api/schema.py
rekuest/collection/__init__.py
rekuest/collection/collector.py
rekuest/collection/shelve.py
rekuest/contrib/arkitekt/websocket_agent_transport.py
rekuest/contrib/arkitekt/websocket_postman_transport.py
rekuest/contrib/rath/set_assignation_link.py
rekuest/definition/__init__.py
rekuest/definition/define.py
rekuest/definition/errors.py
rekuest/definition/guards.py
rekuest/definition/registry.py
rekuest/definition/utils.py
rekuest/definition/validate.py
rekuest/effects.py
rekuest/errors.py
rekuest/funcs.py
rekuest/messages.py
rekuest/postmans/__init__.py
rekuest/postmans/base.py
rekuest/postmans/errors.py
rekuest/postmans/graphql.py
rekuest/postmans/stateful.py
rekuest/postmans/transport/__init__.py
rekuest/postmans/transport/base.py
rekuest/postmans/transport/errors.py
rekuest/postmans/transport/mock.py
rekuest/postmans/transport/protocols/__init__.py
rekuest/postmans/transport/protocols/postman_json.py
rekuest/postmans/transport/websocket.py
rekuest/postmans/utils.py
rekuest/postmans/vars.py
rekuest/qt/__init__.py
rekuest/qt/builders.py
rekuest/rath.py
rekuest-0.2.29.dist-info/METADATA
rekuest-0.2.29.dist-info/WHEEL
rekuest-0.2.29.dist-info/RECORD
