Metadata-Version: 2.1
Name: rekuest
Version: 0.2.29
Summary: rpc and node backbone
License: CC BY-NC 3.0
Author: jhnnsrs
Author-email: jhnnsrs@gmail.com
Requires-Python: >=3.7,<4.0
Classifier: License :: Other/Proprietary License
Classifier: Programming Language :: Python :: 3
Classifier: Programming Language :: Python :: 3.7
Classifier: Programming Language :: Python :: 3.8
Classifier: Programming Language :: Python :: 3.9
Classifier: Programming Language :: Python :: 3.10
Classifier: Programming Language :: Python :: 3.11
Requires-Dist: aenum (>=3.1.15,<4.0.0)
Requires-Dist: annotated-types (>=0.4.0,<0.5.0)
Requires-Dist: docstring-parser (>=0.11)
Requires-Dist: inflection (>=0.5.1,<0.6.0)
Requires-Dist: pydantic (>=1.9.0,<=2.0)
Requires-Dist: rath (>=0.4.7)
Requires-Dist: websockets (>=10.0,<11.0)
